{
    "key": "group_653f74dda05ca",
    "title": "Bloc documents à télécharger",
    "fields": [
        {
            "key": "field_653f74dda9146",
            "label": "Bloc documents à télécharger",
            "name": "",
            "aria-label": "",
            "type": "accordion",
            "instructions": "Bloc sur fond orange avec documents PDF à télécharger.",
            "required": 0,
            "conditional_logic": 0,
            "wrapper": {
                "width": "",
                "class": "",
                "id": ""
            },
            "open": 0,
            "multi_expand": 0,
            "endpoint": 0
        },
        {
            "key": "field_653f7cbd55463",
            "label": "Documents",
            "name": "docs",
            "aria-label": "",
            "type": "repeater",
            "instructions": "",
            "required": 0,
            "conditional_logic": 0,
            "wrapper": {
                "width": "",
                "class": "",
                "id": ""
            },
            "layout": "block",
            "pagination": 0,
            "min": 0,
            "max": 0,
            "collapsed": "field_653f7ccb55464",
            "button_label": "Ajouter un élément",
            "rows_per_page": 20,
            "sub_fields": [
                {
                    "key": "field_653f7ccb55464",
                    "label": "Titre du document",
                    "name": "titre",
                    "aria-label": "",
                    "type": "text",
                    "instructions": "",
                    "required": 0,
                    "conditional_logic": 0,
                    "wrapper": {
                        "width": "",
                        "class": "",
                        "id": ""
                    },
                    "default_value": "",
                    "maxlength": "",
                    "placeholder": "",
                    "prepend": "",
                    "append": "",
                    "parent_repeater": "field_653f7cbd55463"
                },
                {
                    "key": "field_6540bfdf95a9a",
                    "label": "Description du fichier (type et taille)",
                    "name": "description",
                    "aria-label": "",
                    "type": "text",
                    "instructions": "",
                    "required": 0,
                    "conditional_logic": 0,
                    "wrapper": {
                        "width": "",
                        "class": "",
                        "id": ""
                    },
                    "default_value": "Document Adobe Acrobat 1.0 MB",
                    "maxlength": "",
                    "placeholder": "",
                    "prepend": "",
                    "append": "",
                    "parent_repeater": "field_653f7cbd55463"
                },
                {
                    "key": "field_653f7cd555465",
                    "label": "Fichier",
                    "name": "file",
                    "aria-label": "",
                    "type": "file",
                    "instructions": "",
                    "required": 0,
                    "conditional_logic": 0,
                    "wrapper": {
                        "width": "",
                        "class": "",
                        "id": ""
                    },
                    "return_format": "array",
                    "library": "all",
                    "min_size": "",
                    "max_size": "",
                    "mime_types": "",
                    "parent_repeater": "field_653f7cbd55463"
                }
            ]
        }
    ],
    "location": [
        [
            {
                "param": "block",
                "operator": "==",
                "value": "acf\/telecharger"
            }
        ]
    ],
    "menu_order": 0,
    "position": "normal",
    "style": "default",
    "label_placement": "top",
    "instruction_placement": "label",
    "hide_on_screen": "",
    "active": true,
    "description": "",
    "show_in_rest": 0,
    "modified": 1698742282
}
